svtools/__init__.py
svtools/_version.py
svtools/afreq.py
svtools/bedpe.py
svtools/bedpesort.py
svtools/bedpetobed12.py
svtools/bedpetovcf.py
svtools/bedpetovcfconverter.py
svtools/breakpoint.py
svtools/cli.py
svtools/cluster.py
svtools/copynumber.py
svtools/exceptions.py
svtools/external_cmd.py
svtools/genotype.py
svtools/l_bp.py
svtools/lmerge.py
svtools/lmerge_ins.py
svtools/logspace.py
svtools/lsort.py
svtools/prune.py
svtools/sv_classifier.py
svtools/utils.py
svtools/varlookup.py
svtools/vcfpaste.py
svtools/vcfsort.py
svtools/vcftobedpe.py
svtools/vcftobedpeconverter.py
svtools/bin/bedpesort
svtools/bin/vcfsort
svtools/vcf/__init__.py
svtools/vcf/file.py
svtools/vcf/genotype.py
svtools/vcf/variant.py
svtools-0.5.1.data/scripts/create_coordinates
svtools-0.5.1.dist-info/LICENSE.txt
svtools-0.5.1.dist-info/METADATA
svtools-0.5.1.dist-info/WHEEL
svtools-0.5.1.dist-info/entry_points.txt
svtools-0.5.1.dist-info/top_level.txt
svtools-0.5.1.dist-info/RECORD
