Metadata-Version: 2.1
Name: svtools
Version: 0.5.1
Summary: Tools for processing and analyzing structural variants
Home-page: https://github.com/hall-lab/svtools
Author: Ira Hall lab
Author-email: dlarson@genome.wustl.edu
License: MIT
Keywords: genomics structural variants sv bioinformatics
Platform: UNKNOWN
Classifier: Development Status :: 3 - Alpha
Classifier: Intended Audience :: Science/Research
Classifier: Topic :: Scientific/Engineering :: Bio-Informatics
Classifier: License :: OSI Approved :: MIT License
Classifier: Programming Language :: Python :: 2.7
Requires-Dist: svtyper (==0.7.1)
Requires-Dist: numpy
Requires-Dist: scipy
Requires-Dist: statsmodels
Requires-Dist: pandas (==0.19.2)
Requires-Dist: setuptools
Requires-Dist: google-auth
Requires-Dist: google-cloud-storage
Requires-Dist: google-compute-engine
Requires-Dist: crcmod
Requires-Dist: logzero
